labelboxutils/__init__.py
labelboxutils/_version.py
labelboxutils/ui/__init__.py
labelboxutils/ui/labelbox_export_json_app.py
labelboxutils/ui/labelbox_export_json_command_line.py
Labelbox_Utils-0.0.3.dist-info/LICENSE
Labelbox_Utils-0.0.3.dist-info/METADATA
Labelbox_Utils-0.0.3.dist-info/WHEEL
Labelbox_Utils-0.0.3.dist-info/entry_points.txt
Labelbox_Utils-0.0.3.dist-info/top_level.txt
Labelbox_Utils-0.0.3.dist-info/RECORD
