Metadata-Version: 2.1
Name: Labelbox-Utils
Version: 0.0.3
Summary: Utils for working with Labelbox
Home-page: https://weisslab.cs.ucl.ac.uk/WEISS/SoftwareRepositories/LabelboxUtils
Author: Matt Clarkson
Author-email: m.clarkson@ucl.ac.uk
License: Apache Software License 2.0
Keywords: medical imaging
Platform: UNKNOWN
Classifier: Development Status :: 3 - Alpha
Classifier: Intended Audience :: Developers
Classifier: Intended Audience :: Healthcare Industry
Classifier: Intended Audience :: Information Technology
Classifier: Intended Audience :: Science/Research
Classifier: License :: OSI Approved :: Apache Software License
Classifier: Programming Language :: Python
Classifier: Programming Language :: Python :: 2
Classifier: Programming Language :: Python :: 3
Classifier: Topic :: Scientific/Engineering :: Information Analysis
Classifier: Topic :: Scientific/Engineering :: Medical Science Apps.
Requires-Dist: six
Requires-Dist: numpy
Requires-Dist: ipykernel
Requires-Dist: nbsphinx
Requires-Dist: opencv-contrib-python
